getcontext/__init__.py
getcontext/generated/__init__.py
getcontext/generated/_client.py
getcontext/generated/_configuration.py
getcontext/generated/_patch.py
getcontext/generated/_serialization.py
getcontext/generated/_vendor.py
getcontext/generated/aio/__init__.py
getcontext/generated/aio/_client.py
getcontext/generated/aio/_configuration.py
getcontext/generated/aio/_patch.py
getcontext/generated/aio/_vendor.py
getcontext/generated/aio/operations/__init__.py
getcontext/generated/aio/operations/_operations.py
getcontext/generated/aio/operations/_patch.py
getcontext/generated/models/__init__.py
getcontext/generated/models/_enums.py
getcontext/generated/models/_models.py
getcontext/generated/models/_patch.py
getcontext/generated/operations/__init__.py
getcontext/generated/operations/_operations.py
getcontext/generated/operations/_patch.py
getcontext/generated/py.typed
getcontext/token.py
context_python-0.18.0.dist-info/LICENSE.md
context_python-0.18.0.dist-info/METADATA
context_python-0.18.0.dist-info/WHEEL
context_python-0.18.0.dist-info/RECORD
