Metadata-Version: 2.1
Name: context-python
Version: 0.18.0
Summary: Python SDK for the Context API
License: LICENSE.md
Keywords: context,api,sdk
Author: Alex Gamble
Author-email: alex@context.ai
Requires-Python: >=3.10,<4.0
Classifier: License :: Other/Proprietary License
Classifier: Programming Language :: Python :: 3
Classifier: Programming Language :: Python :: 3.10
Classifier: Programming Language :: Python :: 3.11
Classifier: Programming Language :: Python :: 3.12
Requires-Dist: aiohttp (>=3.8.4,<4.0.0)
Requires-Dist: azure-core (<2.0.0)
Requires-Dist: azure-mgmt-core (<2.0.0)
Requires-Dist: msrest (<1.0.0)
